pyEchosign/__init__.py
pyEchosign/classes/__init__.py
pyEchosign/classes/account.py
pyEchosign/classes/agreement.py
pyEchosign/classes/documents.py
pyEchosign/classes/library_document.py
pyEchosign/classes/users.py
pyEchosign/exceptions/__init__.py
pyEchosign/exceptions/echosign.py
pyEchosign/exceptions/internal.py
pyEchosign/utils/__init__.py
pyEchosign/utils/endpoints.py
pyEchosign/utils/handle_response.py
pyEchosign/utils/request_parameters.py
pyEchosign/utils/utils.py
pyEchosign-1.0.1.dist-info/DESCRIPTION.rst
pyEchosign-1.0.1.dist-info/METADATA
pyEchosign-1.0.1.dist-info/RECORD
pyEchosign-1.0.1.dist-info/WHEEL
pyEchosign-1.0.1.dist-info/metadata.json
pyEchosign-1.0.1.dist-info/top_level.txt
