Metadata-Version: 2.0
Name: pyEchosign
Version: 1.0.1
Summary: Connect to the Echosign API without constructing HTTP requests
Home-page: https://gitlab.com/jensastrup/pyEchosign
Author: Jens Astrup
Author-email: jensaiden@gmail.com
License: MIT
Keywords: adobe echosign
Platform: UNKNOWN
Classifier: Development Status :: 2 - Pre-Alpha
Classifier: Intended Audience :: Developers
Classifier: Topic :: Office/Business
Classifier: License :: OSI Approved :: MIT License
Classifier: Programming Language :: Python :: 2.7
Classifier: Programming Language :: Python :: 3
Classifier: Programming Language :: Python :: 3.5
Classifier: Programming Language :: Python :: 3.6
Classifier: Natural Language :: English
Requires-Dist: requests (<3.0.0,>=2.12.4)
Requires-Dist: arrow (<1.0.0,>=0.10.0)
